dev/pypsa_copies.py
remind_pypsa_coupling-0.1.3.dist-info/licenses/LICENSE
rpycpl/__init__.py
rpycpl/capacities_etl.py
rpycpl/coupled_cfg.py
rpycpl/disagg.py
rpycpl/etl.py
rpycpl/technoecon_etl.py
rpycpl/utils.py
remind_pypsa_coupling-0.1.3.dist-info/METADATA
remind_pypsa_coupling-0.1.3.dist-info/WHEEL
remind_pypsa_coupling-0.1.3.dist-info/top_level.txt
remind_pypsa_coupling-0.1.3.dist-info/RECORD
