Metadata-Version: 2.4
Name: REMIND-PyPSA-coupling
Version: 0.1.3
Summary: Tools to couple the REMIND IAM and PyPSA power models
Project-URL: Homepage, https://github.com/pik-piam/Remind-PyPSA-coupling/
Project-URL: Documentation, https://pik-piam.github.io/Remind-PyPSA-coupling/
Requires-Python: >=3.12
License-File: LICENSE
Requires-Dist: numpy>1.9
Requires-Dist: pandas>2
Requires-Dist: pyyaml
Requires-Dist: country_converter
Requires-Dist: pytest
Provides-Extra: jupyter
Requires-Dist: ipykernel; extra == "jupyter"
Requires-Dist: ipython; extra == "jupyter"
Provides-Extra: gdx
Requires-Dist: gamspy; extra == "gdx"
Provides-Extra: docu
Requires-Dist: mkdocs; extra == "docu"
Requires-Dist: mkdocs_gen_files; extra == "docu"
Requires-Dist: mkdocstrings[python]; extra == "docu"
Requires-Dist: mkdocs-literate-nav; extra == "docu"
Requires-Dist: mkdocs-material; extra == "docu"
Requires-Dist: mkdocs-include-dir-to-nav; extra == "docu"
Dynamic: license-file
